elisa/__init__.py
elisa/atm.py
elisa/buffer.py
elisa/const.py
elisa/ld.py
elisa/logger.py
elisa/umpy.py
elisa/units.py
elisa/utils.py
elisa/analytics/__init__.py
elisa/analytics/tasks.py
elisa/analytics/transform.py
elisa/analytics/binary_fit/__init__.py
elisa/analytics/binary_fit/io_tools.py
elisa/analytics/binary_fit/lc_fit.py
elisa/analytics/binary_fit/least_squares.py
elisa/analytics/binary_fit/mcmc.py
elisa/analytics/binary_fit/mixins.py
elisa/analytics/binary_fit/plot.py
elisa/analytics/binary_fit/rv_fit.py
elisa/analytics/binary_fit/shared.py
elisa/analytics/binary_fit/summary.py
elisa/analytics/dataset/__init__.py
elisa/analytics/dataset/base.py
elisa/analytics/dataset/transform.py
elisa/analytics/dataset/utils.py
elisa/analytics/dataset/graphic/__init__.py
elisa/analytics/dataset/graphic/plot.py
elisa/analytics/models/__init__.py
elisa/analytics/models/cost_fns.py
elisa/analytics/models/lc.py
elisa/analytics/models/rv.py
elisa/analytics/models/serializers.py
elisa/analytics/params/__init__.py
elisa/analytics/params/bonds.py
elisa/analytics/params/conf.py
elisa/analytics/params/parameters.py
elisa/analytics/params/result_handler.py
elisa/analytics/params/transform.py
elisa/analytics/tools/__init__.py
elisa/analytics/tools/bvi.py
elisa/analytics/tools/horizon.py
elisa/analytics/tools/utils.py
elisa/base/__init__.py
elisa/base/body.py
elisa/base/container.py
elisa/base/error.py
elisa/base/spot.py
elisa/base/star.py
elisa/base/system.py
elisa/base/transform.py
elisa/base/curves/__init__.py
elisa/base/curves/rv_point.py
elisa/base/curves/utils.py
elisa/base/graphics/__init__.py
elisa/base/graphics/plot.py
elisa/base/orbit/__init__.py
elisa/base/orbit/orbit.py
elisa/base/surface/__init__.py
elisa/base/surface/coverage.py
elisa/base/surface/faces.py
elisa/base/surface/gravity.py
elisa/base/surface/mesh.py
elisa/base/surface/temperature.py
elisa/binary_system/__init__.py
elisa/binary_system/container.py
elisa/binary_system/dynamic.py
elisa/binary_system/model.py
elisa-0.5.1.dist-info/LICENCE
elisa-0.5.1.dist-info/METADATA
elisa-0.5.1.dist-info/WHEEL
elisa-0.5.1.dist-info/entry_points.txt
elisa-0.5.1.dist-info/top_level.txt
elisa-0.5.1.dist-info/RECORD
